celery_starter/__init__.py
celery_starter/_localization.py
celery_starter/apps.py
celery_starter/management/__init__.py
celery_starter/management/commands/__init__.py
celery_starter/management/commands/runcelery.py
celery_starter-1.0.9.dist-info/LICENSE
celery_starter-1.0.9.dist-info/METADATA
celery_starter-1.0.9.dist-info/WHEEL
celery_starter-1.0.9.dist-info/entry_points.txt
celery_starter-1.0.9.dist-info/top_level.txt
celery_starter-1.0.9.dist-info/RECORD
